liteflow.providers.azure-0.3.1-py3.6-nspkg.pth
liteflow/providers/azure/__init__.py
liteflow/providers/azure/azure_lock_provider.py
liteflow/providers/azure/azure_queue_provider.py
liteflow.providers.azure-0.3.1.dist-info/METADATA
liteflow.providers.azure-0.3.1.dist-info/RECORD
liteflow.providers.azure-0.3.1.dist-info/WHEEL
liteflow.providers.azure-0.3.1.dist-info/namespace_packages.txt
liteflow.providers.azure-0.3.1.dist-info/top_level.txt
