Metadata-Version: 2.1
Name: liteflow.providers.azure
Version: 0.3.1
Summary: Azure queue and distributed lock providers for LiteFlow
Home-page: https://github.com/danielgerlag/liteflow
Author: Daniel Gerlag
Author-email: daniel@gerlag.ca
License: MIT
Platform: UNKNOWN
Classifier: Programming Language :: Python :: 3.6
Classifier: License :: OSI Approved :: MIT License
Classifier: Operating System :: OS Independent
Requires-Python: >=3.6
Requires-Dist: liteflow.core (>=0.3)
Requires-Dist: azure-storage-blob (>=1.1.0)
Requires-Dist: azure-storage-queue (>=1.1.0)
Requires-Dist: python-interface (>=1.4.0)
